nonebot_plugin_wx4/__init__.py
nonebot_plugin_wx4/config.py
nonebot_plugin_wx4/ConversationStorage.py
nonebot_plugin_wx4-1.3.1.dist-info/LICENSE
nonebot_plugin_wx4-1.3.1.dist-info/METADATA
nonebot_plugin_wx4-1.3.1.dist-info/WHEEL
nonebot_plugin_wx4-1.3.1.dist-info/RECORD
